{
  "objectInfo" : {
    "id" : "6qXaUMs9Dk0hcnyDF1gFif",
    "name" : "SimplifyXML",
    "type" : "PROCESS",
    "metadata" : {
      "modelVersion" : {
        "major" : 1,
        "minor" : 0
      },
      "repoInfo" : {
        "repoHandle" : "PwLdqcgm8lnCmp6-gt-2781-2019-10-04T10:16:15.666Z::pd.xml"
      },
      "contextAttributes" : null,
      "additionalInfo" : {
        "description" : "",
        "contentType" : "application/json; charset=utf-8",
        "documentState" : "VALID"
      }
    }
  },
  "dataFileExtension" : "xml",
  "objectRefs" : [ ]
}